MANIFEST.in
README.markdown
requirements.txt
setup.py
pin/__init__.py
pin/plugins/__init__.py
pin/plugins/pinfab.py
pin/plugins/pinfabric.py
pinfab.egg-info/PKG-INFO
pinfab.egg-info/SOURCES.txt
pinfab.egg-info/dependency_links.txt
pinfab.egg-info/namespace_packages.txt
pinfab.egg-info/requires.txt
pinfab.egg-info/top_level.txt